{
  "format": "overlay_json_v1",
  "kind": "morph_bundle",
  "version": 1,
  "asset_id": "morph_0520-male-peak-performance-v2",
  "name": "Male Peak Performance V2",
  "source_file": "0520-male-peak-performance-v2.rbxmx",
  "anchor": "Head",
  "root_cframe": {
    "position": [
      -1027.17407,
      39.3645554,
      -208.366394
    ],
    "rotation": [
      -0.730345428,
      -2.1526278e-10,
      0.683077991,
      1.57726205e-8,
      1,
      1.71791861e-8,
      -0.683077991,
      2.33206698e-8,
      -0.730345428
    ]
  },
  "class_counts": {
    "Folder": 1,
    "Model": 5,
    "Part": 11,
    "MeshPart": 5
  },
  "nodes": [
    {
      "id": "RBX8C4DF6F6CBAC4A7AA6303202FE594348",
      "parent": null,
      "class": "Folder",
      "name": "Male Peak Performance V2",
      "properties": {
        "Name": "Male Peak Performance V2"
      }
    },
    {
      "id": "RBX33399CAB07B941E2B5430D8F6CF036D2",
      "parent": "RBX8C4DF6F6CBAC4A7AA6303202FE594348",
      "class": "Model",
      "name": "BodyTorso",
      "properties": {
        "PrimaryPart": null,
        "Name": "BodyTorso"
      }
    },
    {
      "id": "RBX23842ADFB106406A8A6761EA23375D91",
      "parent": "RBX33399CAB07B941E2B5430D8F6CF036D2",
      "class": "Part",
      "name": "Middle",
      "properties": {
        "shape": 1,
        "Anchored": true,
        "CanCollide": false,
        "CanQuery": true,
        "CanTouch": true,
        "Color3uint8": [
          1,
          1,
          0.8
        ],
        "Massless": false,
        "Material": 256,
        "PivotOffset": {
          "position": [
            0,
            0,
            0
          ],
          "rotation": [
            1,
            0,
            0,
            0,
            1,
            0,
            0,
            0,
            1
          ]
        },
        "Reflectance": 0,
        "Transparency": 1,
        "size": [
          0.100000001,
          0.100000001,
          0.100000001
        ],
        "Name": "Middle",
        "LocalCFrame": {
          "position": [
            0,
            0,
            0
          ],
          "rotation": [
            1,
            0,
            0,
            0,
            1,
            0,
            0,
            0,
            1
          ]
        }
      }
    },
    {
      "id": "RBX261A2BFC48D14A8682DFCA39790E41CA",
      "parent": "RBX33399CAB07B941E2B5430D8F6CF036D2",
      "class": "MeshPart",
      "name": "Torso",
      "properties": {
        "MeshId": "rbxassetid://10395947978",
        "RenderFidelity": 1,
        "TextureID": null,
        "Anchored": true,
        "CanCollide": false,
        "CanQuery": true,
        "CanTouch": true,
        "Color3uint8": [
          1,
          1,
          0.8
        ],
        "Massless": false,
        "Material": 272,
        "PivotOffset": {
          "position": [
            0,
            0,
            0
          ],
          "rotation": [
            1,
            0,
            0,
            0,
            1,
            0,
            0,
            0,
            1
          ]
        },
        "Reflectance": 0,
        "Transparency": 0,
        "size": [
          2.15365696,
          2.11259985,
          1.18372977
        ],
        "Name": "Torso",
        "LocalCFrame": {
          "position": [
            0.000211,
            -0.026123,
            -0.002454
          ],
          "rotation": [
            1,
            0,
            0,
            0,
            1,
            0,
            0,
            0,
            1
          ]
        }
      }
    },
    {
      "id": "RBXFA98D797448E40A49369DE06E251D055",
      "parent": "RBX8C4DF6F6CBAC4A7AA6303202FE594348",
      "class": "Model",
      "name": "BodyRightLeg",
      "properties": {
        "PrimaryPart": null,
        "Name": "BodyRightLeg"
      }
    },
    {
      "id": "RBX5BF782D9947841F49E5F18F316FB566F",
      "parent": "RBXFA98D797448E40A49369DE06E251D055",
      "class": "Part",
      "name": "Middle",
      "properties": {
        "shape": 1,
        "Anchored": true,
        "CanCollide": false,
        "CanQuery": true,
        "CanTouch": true,
        "Color3uint8": [
          1,
          1,
          0.8
        ],
        "Massless": false,
        "Material": 256,
        "PivotOffset": {
          "position": [
            0,
            0,
            0
          ],
          "rotation": [
            1,
            0,
            0,
            0,
            1,
            0,
            0,
            0,
            1
          ]
        },
        "Reflectance": 0,
        "Transparency": 1,
        "size": [
          0.100000001,
          0.100000001,
          0.100000001
        ],
        "Name": "Middle",
        "LocalCFrame": {
          "position": [
            0.499578,
            -1.975689,
            -0.00036
          ],
          "rotation": [
            1,
            0,
            0,
            0,
            1,
            0,
            0,
            0,
            1
          ]
        }
      }
    },
    {
      "id": "RBXE9C71B912FE84677A51D5FC3AAB8F1CF",
      "parent": "RBXFA98D797448E40A49369DE06E251D055",
      "class": "MeshPart",
      "name": "Right Leg",
      "properties": {
        "MeshId": "rbxassetid://6257082295",
        "RenderFidelity": 1,
        "TextureID": null,
        "Anchored": true,
        "CanCollide": false,
        "CanQuery": true,
        "CanTouch": true,
        "Color3uint8": [
          1,
          1,
          0.8
        ],
        "Massless": false,
        "Material": 272,
        "PivotOffset": {
          "position": [
            0,
            0,
            0
          ],
          "rotation": [
            1,
            0,
            0,
            0,
            1,
            0,
            0,
            0,
            1
          ]
        },
        "Reflectance": 0,
        "Transparency": 0,
        "size": [
          1.25501275,
          2.49443412,
          1.24915195
        ],
        "Name": "Right Leg",
        "LocalCFrame": {
          "position": [
            0.501555,
            -1.904202,
            0.064836
          ],
          "rotation": [
            0.00183,
            0,
            0.999998,
            0,
            1,
            0,
            -0.999998,
            0,
            0.00183
          ]
        }
      }
    },
    {
      "id": "RBX3B677E39A0DF429DBBA19CFAB9F49F60",
      "parent": "RBXE9C71B912FE84677A51D5FC3AAB8F1CF",
      "class": "Part",
      "name": "Joint",
      "properties": {
        "shape": 1,
        "Anchored": false,
        "CanCollide": true,
        "CanQuery": true,
        "CanTouch": true,
        "Color3uint8": [
          0.768627,
          0.156863,
          0.109804
        ],
        "Massless": false,
        "Material": 256,
        "PivotOffset": {
          "position": [
            0,
            0,
            0
          ],
          "rotation": [
            1,
            0,
            0,
            0,
            1,
            0,
            0,
            0,
            1
          ]
        },
        "Reflectance": 0,
        "Transparency": 1,
        "size": [
          0.0533739217,
          0.0533739217,
          0.0533739217
        ],
        "Name": "Joint",
        "LocalCFrame": {
          "position": [
            -3986.078293,
            -650.838611,
            -3717.975969
          ],
          "rotation": [
            0.318567,
            -0.081241,
            0.944413,
            -0.019134,
            -0.996669,
            -0.079282,
            0.947707,
            0.007187,
            -0.31906
          ]
        }
      }
    },
    {
      "id": "RBXA3D07B3CC8034F4C834DD749E31D1ACC",
      "parent": "RBXE9C71B912FE84677A51D5FC3AAB8F1CF",
      "class": "Part",
      "name": "Joint",
      "properties": {
        "shape": 1,
        "Anchored": false,
        "CanCollide": true,
        "CanQuery": true,
        "CanTouch": true,
        "Color3uint8": [
          0.768627,
          0.156863,
          0.109804
        ],
        "Massless": false,
        "Material": 256,
        "PivotOffset": {
          "position": [
            0,
            0,
            0
          ],
          "rotation": [
            1,
            0,
            0,
            0,
            1,
            0,
            0,
            0,
            1
          ]
        },
        "Reflectance": 0,
        "Transparency": 1,
        "size": [
          0.0533739217,
          0.0533739217,
          0.0533739217
        ],
        "Name": "Joint",
        "LocalCFrame": {
          "position": [
            -3984.71773,
            -650.838611,
            -3717.173268
          ],
          "rotation": [
            -0.039404,
            0.67117,
            -0.740256,
            -0.998973,
            -0.009885,
            0.044212,
            0.022356,
            0.741238,
            0.67087
          ]
        }
      }
    },
    {
      "id": "RBXAE81282DA62546F0AC867CF6D9A7A8C3",
      "parent": "RBXE9C71B912FE84677A51D5FC3AAB8F1CF",
      "class": "Part",
      "name": "Joint",
      "properties": {
        "shape": 1,
        "Anchored": false,
        "CanCollide": true,
        "CanQuery": true,
        "CanTouch": true,
        "Color3uint8": [
          0.768627,
          0.156863,
          0.109804
        ],
        "Massless": false,
        "Material": 256,
        "PivotOffset": {
          "position": [
            0,
            0,
            0
          ],
          "rotation": [
            1,
            0,
            0,
            0,
            1,
            0,
            0,
            0,
            1
          ]
        },
        "Reflectance": 0,
        "Transparency": 1,
        "size": [
          0.0533739217,
          0.0533739217,
          0.0533739217
        ],
        "Name": "Joint",
        "LocalCFrame": {
          "position": [
            -3985.045093,
            -650.830432,
            -3716.631093
          ],
          "rotation": [
            0.033584,
            0.979914,
            -0.19657,
            -0.999143,
            0.028157,
            -0.03034,
            -0.024195,
            0.197421,
            0.98002
          ]
        }
      }
    },
    {
      "id": "RBX7D0D59CFD6174209A4F8A09FBECDAEB2",
      "parent": "RBX8C4DF6F6CBAC4A7AA6303202FE594348",
      "class": "Model",
      "name": "BodyRightArm",
      "properties": {
        "PrimaryPart": null,
        "Name": "BodyRightArm"
      }
    },
    {
      "id": "RBXB01F44E66D94426D9A62B20CE004D9C9",
      "parent": "RBX7D0D59CFD6174209A4F8A09FBECDAEB2",
      "class": "Part",
      "name": "Middle",
      "properties": {
        "shape": 1,
        "Anchored": true,
        "CanCollide": false,
        "CanQuery": true,
        "CanTouch": true,
        "Color3uint8": [
          1,
          1,
          0.8
        ],
        "Massless": false,
        "Material": 256,
        "PivotOffset": {
          "position": [
            0,
            0,
            0
          ],
          "rotation": [
            1,
            0,
            0,
            0,
            1,
            0,
            0,
            0,
            1
          ]
        },
        "Reflectance": 0,
        "Transparency": 1,
        "size": [
          0.100000001,
          0.100000001,
          0.100000001
        ],
        "Name": "Middle",
        "LocalCFrame": {
          "position": [
            1.500231,
            -0.00779,
            -0.010208
          ],
          "rotation": [
            0.999935,
            -0.001048,
            0.01136,
            0.001146,
            0.999962,
            -0.008637,
            -0.011351,
            0.008649,
            0.999898
          ]
        }
      }
    },
    {
      "id": "RBX134EA8DDFD70440396035B847C90C014",
      "parent": "RBX7D0D59CFD6174209A4F8A09FBECDAEB2",
      "class": "MeshPart",
      "name": "Right Arm",
      "properties": {
        "MeshId": "rbxassetid://8820696292",
        "RenderFidelity": 1,
        "TextureID": null,
        "Anchored": true,
        "CanCollide": false,
        "CanQuery": true,
        "CanTouch": true,
        "Color3uint8": [
          1,
          1,
          0.8
        ],
        "Massless": false,
        "Material": 272,
        "PivotOffset": {
          "position": [
            0,
            0,
            0
          ],
          "rotation": [
            1,
            0,
            0,
            0,
            1,
            0,
            0,
            0,
            1
          ]
        },
        "Reflectance": 0,
        "Transparency": 0,
        "size": [
          1.01999998,
          2.02999997,
          1.09300005
        ],
        "Name": "Right Arm",
        "LocalCFrame": {
          "position": [
            1.500711,
            -0.00808,
            -0.009885
          ],
          "rotation": [
            -0.999935,
            -0.001048,
            -0.01136,
            -0.001146,
            0.999962,
            0.008637,
            0.011351,
            0.008649,
            -0.999898
          ]
        }
      }
    },
    {
      "id": "RBX8B9F9126A6DF4C6588B7C06432B69E75",
      "parent": "RBX8C4DF6F6CBAC4A7AA6303202FE594348",
      "class": "Model",
      "name": "BodyLeftLeg",
      "properties": {
        "PrimaryPart": null,
        "Name": "BodyLeftLeg"
      }
    },
    {
      "id": "RBX2CB37CC15A384885B6017581D475AD90",
      "parent": "RBX8B9F9126A6DF4C6588B7C06432B69E75",
      "class": "Part",
      "name": "Middle",
      "properties": {
        "shape": 1,
        "Anchored": true,
        "CanCollide": false,
        "CanQuery": true,
        "CanTouch": true,
        "Color3uint8": [
          1,
          1,
          0.8
        ],
        "Massless": false,
        "Material": 256,
        "PivotOffset": {
          "position": [
            0,
            0,
            0
          ],
          "rotation": [
            1,
            0,
            0,
            0,
            1,
            0,
            0,
            0,
            1
          ]
        },
        "Reflectance": 0,
        "Transparency": 1,
        "size": [
          0.100000001,
          0.100000001,
          0.100000001
        ],
        "Name": "Middle",
        "LocalCFrame": {
          "position": [
            -0.500176,
            -1.970501,
            -0.000105
          ],
          "rotation": [
            1,
            0,
            0,
            0,
            1,
            0,
            0,
            0,
            1
          ]
        }
      }
    },
    {
      "id": "RBXE0AC4A0C1BD64433B5BBB219231713B2",
      "parent": "RBX8B9F9126A6DF4C6588B7C06432B69E75",
      "class": "MeshPart",
      "name": "Left Leg",
      "properties": {
        "MeshId": "rbxassetid://6257247882",
        "RenderFidelity": 1,
        "TextureID": null,
        "Anchored": true,
        "CanCollide": false,
        "CanQuery": true,
        "CanTouch": true,
        "Color3uint8": [
          1,
          1,
          0.8
        ],
        "Massless": false,
        "Material": 272,
        "PivotOffset": {
          "position": [
            0,
            0,
            0
          ],
          "rotation": [
            1,
            0,
            0,
            0,
            1,
            0,
            0,
            0,
            1
          ]
        },
        "Reflectance": 0,
        "Transparency": 0,
        "size": [
          1.255,
          2.49399996,
          1.24899995
        ],
        "Name": "Left Leg",
        "LocalCFrame": {
          "position": [
            -0.496007,
            -1.897846,
            0.058505
          ],
          "rotation": [
            0.00183,
            0,
            0.999998,
            0,
            1,
            0,
            -0.999998,
            0,
            0.00183
          ]
        }
      }
    },
    {
      "id": "RBX618EDA544FD84F24BBAA20774567C6F2",
      "parent": "RBXE0AC4A0C1BD64433B5BBB219231713B2",
      "class": "Part",
      "name": "Joint",
      "properties": {
        "shape": 1,
        "Anchored": false,
        "CanCollide": true,
        "CanQuery": true,
        "CanTouch": true,
        "Color3uint8": [
          0.768627,
          0.156863,
          0.109804
        ],
        "Massless": false,
        "Material": 256,
        "PivotOffset": {
          "position": [
            0,
            0,
            0
          ],
          "rotation": [
            1,
            0,
            0,
            0,
            1,
            0,
            0,
            0,
            1
          ]
        },
        "Reflectance": 0,
        "Transparency": 1,
        "size": [
          0.0533739217,
          0.0533739217,
          0.0533739217
        ],
        "Name": "Joint",
        "LocalCFrame": {
          "position": [
            -3984.33182,
            -650.838611,
            -3717.298204
          ],
          "rotation": [
            0.062321,
            0.996001,
            0.064015,
            -0.998049,
            0.06195,
            0.007757,
            0.00376,
            -0.064373,
            0.997919
          ]
        }
      }
    },
    {
      "id": "RBX8544939E802741B09FBA75E076D1FFDC",
      "parent": "RBXE0AC4A0C1BD64433B5BBB219231713B2",
      "class": "Part",
      "name": "Joint",
      "properties": {
        "shape": 1,
        "Anchored": false,
        "CanCollide": true,
        "CanQuery": true,
        "CanTouch": true,
        "Color3uint8": [
          0.768627,
          0.156863,
          0.109804
        ],
        "Massless": false,
        "Material": 256,
        "PivotOffset": {
          "position": [
            0,
            0,
            0
          ],
          "rotation": [
            1,
            0,
            0,
            0,
            1,
            0,
            0,
            0,
            1
          ]
        },
        "Reflectance": 0,
        "Transparency": 1,
        "size": [
          0.0533739217,
          0.0533739217,
          0.0533739217
        ],
        "Name": "Joint",
        "LocalCFrame": {
          "position": [
            -3985.391708,
            -650.830432,
            -3718.671614
          ],
          "rotation": [
            -0.008575,
            0.513306,
            0.858163,
            0.999959,
            0.00699,
            0.00581,
            -0.003017,
            0.858177,
            -0.513345
          ]
        }
      }
    },
    {
      "id": "RBX641863E12F3A4A8688A12208829EE6E3",
      "parent": "RBXE0AC4A0C1BD64433B5BBB219231713B2",
      "class": "Part",
      "name": "Joint",
      "properties": {
        "shape": 1,
        "Anchored": false,
        "CanCollide": true,
        "CanQuery": true,
        "CanTouch": true,
        "Color3uint8": [
          0.768627,
          0.156863,
          0.109804
        ],
        "Massless": false,
        "Material": 256,
        "PivotOffset": {
          "position": [
            0,
            0,
            0
          ],
          "rotation": [
            1,
            0,
            0,
            0,
            1,
            0,
            0,
            0,
            1
          ]
        },
        "Reflectance": 0,
        "Transparency": 1,
        "size": [
          0.0533739217,
          0.0533739217,
          0.0533739217
        ],
        "Name": "Joint",
        "LocalCFrame": {
          "position": [
            -3984.089383,
            -650.838611,
            -3717.770971
          ],
          "rotation": [
            -0.073122,
            0.65734,
            0.750038,
            0.995525,
            0.002967,
            0.094454,
            0.059863,
            0.753588,
            -0.654615
          ]
        }
      }
    },
    {
      "id": "RBX560F8175FFF84E52B3080C2D7D5F74AA",
      "parent": "RBX8C4DF6F6CBAC4A7AA6303202FE594348",
      "class": "Model",
      "name": "BodyLeftArm",
      "properties": {
        "PrimaryPart": null,
        "Name": "BodyLeftArm"
      }
    },
    {
      "id": "RBXE840A754119E482B83C64D702942BDDB",
      "parent": "RBX560F8175FFF84E52B3080C2D7D5F74AA",
      "class": "Part",
      "name": "Middle",
      "properties": {
        "shape": 1,
        "Anchored": true,
        "CanCollide": false,
        "CanQuery": true,
        "CanTouch": true,
        "Color3uint8": [
          1,
          1,
          0.8
        ],
        "Massless": false,
        "Material": 256,
        "PivotOffset": {
          "position": [
            0,
            0,
            0
          ],
          "rotation": [
            1,
            0,
            0,
            0,
            1,
            0,
            0,
            0,
            1
          ]
        },
        "Reflectance": 0,
        "Transparency": 1,
        "size": [
          0.100000001,
          0.100000001,
          0.100000001
        ],
        "Name": "Middle",
        "LocalCFrame": {
          "position": [
            -1.502284,
            -0.020794,
            -0.01219
          ],
          "rotation": [
            0.999799,
            0.004005,
            -0.019657,
            -0.004087,
            0.999983,
            -0.004132,
            0.01964,
            0.004211,
            0.999798
          ]
        }
      }
    },
    {
      "id": "RBX08DE5225BC3D4FA0BE1DDEB87AD9CC19",
      "parent": "RBX560F8175FFF84E52B3080C2D7D5F74AA",
      "class": "MeshPart",
      "name": "Left Arm",
      "properties": {
        "MeshId": "rbxassetid://8820695377",
        "RenderFidelity": 1,
        "TextureID": null,
        "Anchored": true,
        "CanCollide": false,
        "CanQuery": true,
        "CanTouch": true,
        "Color3uint8": [
          1,
          1,
          0.8
        ],
        "Massless": false,
        "Material": 272,
        "PivotOffset": {
          "position": [
            0,
            0,
            0
          ],
          "rotation": [
            1,
            0,
            0,
            0,
            1,
            0,
            0,
            0,
            1
          ]
        },
        "Reflectance": 0,
        "Transparency": 0,
        "size": [
          1.01999998,
          2.0309999,
          1.09200001
        ],
        "Name": "Left Arm",
        "LocalCFrame": {
          "position": [
            -1.50231,
            -0.021084,
            -0.011852
          ],
          "rotation": [
            -0.999799,
            0.004005,
            0.019657,
            0.004087,
            0.999983,
            0.004132,
            -0.01964,
            0.004211,
            -0.999798
          ]
        }
      }
    }
  ]
}
