{
  "format": "overlay_json_v1",
  "kind": "morph_bundle",
  "version": 1,
  "asset_id": "morph_0619-jiggle-booty-b",
  "name": "Jiggle Booty (B+)",
  "source_file": "0619-jiggle-booty-b.rbxmx",
  "anchor": "Head",
  "root_cframe": {
    "position": [
      -61.6489983,
      3.73300004,
      1.72899997
    ],
    "rotation": [
      -1,
      0,
      2.08616257e-7,
      0,
      1,
      0,
      -2.08616257e-7,
      0,
      -1
    ]
  },
  "class_counts": {
    "Folder": 1,
    "Model": 3,
    "Part": 3,
    "SpecialMesh": 3,
    "MeshPart": 3
  },
  "nodes": [
    {
      "id": "RBX808B91A365A143619A1E8A8689E0B1D5",
      "parent": null,
      "class": "Folder",
      "name": "Jiggle Booty (B+)",
      "properties": {
        "Name": "Jiggle Booty (B+)"
      }
    },
    {
      "id": "RBXEC359F10DA394465BA30051619ECEC28",
      "parent": "RBX808B91A365A143619A1E8A8689E0B1D5",
      "class": "Model",
      "name": "LowerL",
      "properties": {
        "PrimaryPart": null,
        "Name": "LowerL"
      }
    },
    {
      "id": "RBX30CBB0A3B7E24665BB48F23FF58DE334",
      "parent": "RBXEC359F10DA394465BA30051619ECEC28",
      "class": "Part",
      "name": "Middle",
      "properties": {
        "shape": 1,
        "Anchored": true,
        "CanCollide": false,
        "CanQuery": true,
        "CanTouch": true,
        "Color3uint8": [
          1,
          0,
          0
        ],
        "Massless": false,
        "Material": 272,
        "PivotOffset": {
          "position": [
            0,
            0,
            0
          ],
          "rotation": [
            1,
            0,
            0,
            0,
            1,
            0,
            0,
            0,
            1
          ]
        },
        "Reflectance": 0,
        "Transparency": 0,
        "size": [
          0.209008768,
          0.209008768,
          0.209008768
        ],
        "Name": "Middle",
        "LocalCFrame": {
          "position": [
            0,
            0,
            0
          ],
          "rotation": [
            1,
            0,
            0,
            0,
            1,
            0,
            0,
            0,
            1
          ]
        }
      }
    },
    {
      "id": "RBX3C63E1C2FF5449988346D46DF6D9A5E9",
      "parent": "RBX30CBB0A3B7E24665BB48F23FF58DE334",
      "class": "SpecialMesh",
      "name": "Mesh",
      "properties": {
        "MeshType": 6,
        "MeshId": null,
        "TextureId": null,
        "Offset": [
          0,
          0,
          0
        ],
        "Scale": [
          0,
          0,
          0
        ],
        "VertexColor": [
          1,
          1,
          1
        ],
        "Name": "Mesh"
      }
    },
    {
      "id": "RBXCBDE4C243ACD44ABBD692B9D2FEAC5AB",
      "parent": "RBXEC359F10DA394465BA30051619ECEC28",
      "class": "MeshPart",
      "name": "color5",
      "properties": {
        "MeshId": "rbxassetid://17837346792",
        "RenderFidelity": 0,
        "TextureID": null,
        "Anchored": false,
        "CanCollide": true,
        "CanQuery": true,
        "CanTouch": true,
        "Color3uint8": [
          0.639216,
          0.635294,
          0.647059
        ],
        "Massless": false,
        "Material": 272,
        "PivotOffset": {
          "position": [
            0.0352441296,
            -0.00269521982,
            -8.64836736e-8
          ],
          "rotation": [
            1,
            4.23516474e-22,
            -2.44929371e-16,
            -2.44929371e-16,
            -6.12323426e-17,
            -1,
            -4.23516474e-22,
            1,
            -6.12323426e-17
          ]
        },
        "Reflectance": 0,
        "Transparency": 0,
        "size": [
          1.73968732,
          1.82430184,
          1.73968732
        ],
        "Name": "color5",
        "LocalCFrame": {
          "position": [
            -0.396137,
            -0.032148,
            0.113021
          ],
          "rotation": [
            0.965926,
            0.258819,
            0,
            -0.25,
            0.933013,
            0.258819,
            0.066987,
            -0.25,
            0.965926
          ]
        }
      }
    },
    {
      "id": "RBXE50A086DD6C0455AAA72BB7D10A07162",
      "parent": "RBX808B91A365A143619A1E8A8689E0B1D5",
      "class": "Model",
      "name": "LowerStatic",
      "properties": {
        "PrimaryPart": "RBXE5CF30FA13D94EF39C56361967BDB239",
        "Name": "LowerStatic"
      }
    },
    {
      "id": "RBXE5CF30FA13D94EF39C56361967BDB239",
      "parent": "RBXE50A086DD6C0455AAA72BB7D10A07162",
      "class": "Part",
      "name": "Middle",
      "properties": {
        "shape": 1,
        "Anchored": true,
        "CanCollide": false,
        "CanQuery": true,
        "CanTouch": true,
        "Color3uint8": [
          0.972549,
          0.972549,
          0.972549
        ],
        "Massless": false,
        "Material": 272,
        "PivotOffset": {
          "position": [
            0,
            0,
            0
          ],
          "rotation": [
            1,
            0,
            0,
            0,
            1,
            0,
            0,
            0,
            1
          ]
        },
        "Reflectance": 0,
        "Transparency": 0,
        "size": [
          2,
          2,
          1
        ],
        "Name": "Middle",
        "LocalCFrame": {
          "position": [
            0.249851,
            0.937783,
            -0.510889
          ],
          "rotation": [
            1,
            0,
            0,
            0,
            1,
            0,
            0,
            0,
            1
          ]
        }
      }
    },
    {
      "id": "RBXA59670C64D3941509BF72356C1F5F8B6",
      "parent": "RBXE5CF30FA13D94EF39C56361967BDB239",
      "class": "SpecialMesh",
      "name": "Mesh",
      "properties": {
        "MeshType": 5,
        "MeshId": "rbxassetid://12221758",
        "TextureId": null,
        "Offset": [
          0,
          0,
          0
        ],
        "Scale": [
          1,
          1,
          1
        ],
        "VertexColor": [
          1,
          1,
          1
        ],
        "Name": "Mesh"
      }
    },
    {
      "id": "RBXB336C48BCCA944978396FA9868F8CD54",
      "parent": "RBXE50A086DD6C0455AAA72BB7D10A07162",
      "class": "MeshPart",
      "name": "color5",
      "properties": {
        "MeshId": "rbxassetid://16243955924",
        "RenderFidelity": 1,
        "TextureID": null,
        "Anchored": false,
        "CanCollide": true,
        "CanQuery": true,
        "CanTouch": true,
        "Color3uint8": [
          0.388235,
          0.372549,
          0.384314
        ],
        "Massless": false,
        "Material": 272,
        "PivotOffset": {
          "position": [
            0,
            0.000324690307,
            0
          ],
          "rotation": [
            1,
            -1.99520246e-23,
            -2.44929344e-16,
            -2.44929344e-16,
            -1.62920671e-7,
            -1,
            -1.99520278e-23,
            1,
            -1.62920671e-7
          ]
        },
        "Reflectance": 0,
        "Transparency": 0,
        "size": [
          0.549407721,
          0.399054527,
          0.549407721
        ],
        "Name": "color5",
        "LocalCFrame": {
          "position": [
            0.250004,
            0.03175,
            0.043127
          ],
          "rotation": [
            -1,
            0,
            0,
            0,
            -0.5,
            0.866025,
            0,
            0.866025,
            0.5
          ]
        }
      }
    },
    {
      "id": "RBXE5CD9E6C6849464A836EBE3EAF970969",
      "parent": "RBX808B91A365A143619A1E8A8689E0B1D5",
      "class": "Model",
      "name": "LowerR",
      "properties": {
        "PrimaryPart": null,
        "Name": "LowerR"
      }
    },
    {
      "id": "RBXD1799B7F646B4A06B7746858505A3FAF",
      "parent": "RBXE5CD9E6C6849464A836EBE3EAF970969",
      "class": "Part",
      "name": "Middle",
      "properties": {
        "shape": 1,
        "Anchored": true,
        "CanCollide": false,
        "CanQuery": true,
        "CanTouch": true,
        "Color3uint8": [
          1,
          0,
          0
        ],
        "Massless": false,
        "Material": 272,
        "PivotOffset": {
          "position": [
            0,
            0,
            0
          ],
          "rotation": [
            1,
            0,
            0,
            0,
            1,
            0,
            0,
            0,
            1
          ]
        },
        "Reflectance": 0,
        "Transparency": 0,
        "size": [
          0.209008768,
          0.209008768,
          0.209008768
        ],
        "Name": "Middle",
        "LocalCFrame": {
          "position": [
            0.500004,
            0,
            0
          ],
          "rotation": [
            1,
            0,
            0,
            0,
            1,
            0,
            0,
            0,
            1
          ]
        }
      }
    },
    {
      "id": "RBX5C4D65FDF1594B0F9C00EC0EC4085131",
      "parent": "RBXD1799B7F646B4A06B7746858505A3FAF",
      "class": "SpecialMesh",
      "name": "Mesh",
      "properties": {
        "MeshType": 6,
        "MeshId": null,
        "TextureId": null,
        "Offset": [
          0,
          0,
          0
        ],
        "Scale": [
          0,
          0,
          0
        ],
        "VertexColor": [
          1,
          1,
          1
        ],
        "Name": "Mesh"
      }
    },
    {
      "id": "RBXE1818E44EE684E8DACB1C0FD7A8E0D6F",
      "parent": "RBXE5CD9E6C6849464A836EBE3EAF970969",
      "class": "MeshPart",
      "name": "color5",
      "properties": {
        "MeshId": "rbxassetid://17837346792",
        "RenderFidelity": 0,
        "TextureID": null,
        "Anchored": false,
        "CanCollide": true,
        "CanQuery": true,
        "CanTouch": true,
        "Color3uint8": [
          0.639216,
          0.635294,
          0.647059
        ],
        "Massless": false,
        "Material": 272,
        "PivotOffset": {
          "position": [
            0.0352441296,
            -0.00269521982,
            -8.64836736e-8
          ],
          "rotation": [
            1,
            4.23516474e-22,
            -2.44929371e-16,
            -2.44929371e-16,
            -6.12323426e-17,
            -1,
            -4.23516474e-22,
            1,
            -6.12323426e-17
          ]
        },
        "Reflectance": 0,
        "Transparency": 0,
        "size": [
          1.73968732,
          1.82430184,
          1.73968732
        ],
        "Name": "color5",
        "LocalCFrame": {
          "position": [
            0.896137,
            -0.032148,
            0.11302
          ],
          "rotation": [
            -0.965926,
            -0.258819,
            0,
            -0.25,
            0.933013,
            -0.258819,
            0.066987,
            -0.25,
            -0.965926
          ]
        }
      }
    }
  ]
}
