{
  "format": "overlay_json_v1",
  "kind": "morph_bundle",
  "version": 1,
  "asset_id": "morph_2979-tz-phys-uv-boobs",
  "name": "Tz phys uv boobs",
  "source_file": "2979-tz-phys-uv-boobs.rbxmx",
  "anchor": "UpperTorso",
  "anchor_candidates": [
    "UpperTorso",
    "Torso",
    "HumanoidRootPart",
    "Head"
  ],
  "jiggle": true,
  "root_cframe": {
    "position": [
      -347.743561,
      -18.6600208,
      -549.371765
    ],
    "rotation": [
      1,
      1.33226731e-15,
      -1.08896894e-30,
      1.33226731e-15,
      0.999999523,
      -2.17968068e-15,
      -1.08896894e-30,
      -2.17968068e-15,
      0.999998569
    ]
  },
  "class_counts": {
    "Folder": 1,
    "Model": 1,
    "Part": 2,
    "SpecialMesh": 1,
    "MeshPart": 2,
    "Motor6D": 2,
    "Bone": 4
  },
  "nodes": [
    {
      "id": "RBX2253A60A776445DF81355A670054F5EA",
      "parent": null,
      "class": "Folder",
      "name": "Tz phys uv boobs",
      "properties": {
        "Name": "Tz phys uv boobs"
      }
    },
    {
      "id": "RBX4DD1C48A8ADA4CCAA41B14F3EB849828",
      "parent": "RBX2253A60A776445DF81355A670054F5EA",
      "class": "Model",
      "name": "UpperStatic",
      "properties": {
        "PrimaryPart": "RBXA47C3A5EC5AC43309F1B64B9979E394B",
        "Name": "UpperStatic"
      }
    },
    {
      "id": "RBX07BDAF15B0394BAE93346E398BDFEBC7",
      "parent": "RBX4DD1C48A8ADA4CCAA41B14F3EB849828",
      "class": "Part",
      "name": "Middle",
      "properties": {
        "shape": 1,
        "Anchored": true,
        "CanCollide": false,
        "CanQuery": true,
        "CanTouch": true,
        "Color3uint8": [
          0.972549,
          0.972549,
          0.972549
        ],
        "Massless": false,
        "Material": 272,
        "PivotOffset": {
          "position": [
            0,
            0,
            0
          ],
          "rotation": [
            1,
            0,
            0,
            0,
            1,
            0,
            0,
            0,
            1
          ]
        },
        "Reflectance": 0,
        "Transparency": 0,
        "size": [
          2,
          2,
          1
        ],
        "Name": "Middle",
        "LocalCFrame": {
          "position": [
            -0.15216,
            0.524074,
            -1.066465
          ],
          "rotation": [
            -1,
            0,
            0,
            0,
            0.999999,
            0,
            0,
            0,
            -0.999998
          ]
        }
      }
    },
    {
      "id": "RBXC6A755296D7F47D68007BCCAC6B5C8F7",
      "parent": "RBX07BDAF15B0394BAE93346E398BDFEBC7",
      "class": "SpecialMesh",
      "name": "MaleMesh",
      "properties": {
        "MeshType": 5,
        "MeshId": "rbxassetid://12221758",
        "TextureId": null,
        "Offset": [
          0,
          0,
          0
        ],
        "Scale": [
          1,
          1,
          1
        ],
        "VertexColor": [
          1,
          1,
          1
        ],
        "Name": "MaleMesh"
      }
    },
    {
      "id": "RBX0FDA41449F634F4CACD24450356743B5",
      "parent": "RBX4DD1C48A8ADA4CCAA41B14F3EB849828",
      "class": "MeshPart",
      "name": "Cloth",
      "properties": {
        "HasSkinnedMesh": true,
        "MeshId": "rbxassetid://133733754286824",
        "RenderFidelity": 0,
        "TextureID": "rbxassetid://5364800800",
        "Anchored": false,
        "CanCollide": true,
        "CanQuery": true,
        "CanTouch": true,
        "Color3uint8": [
          0.639216,
          0.635294,
          0.647059
        ],
        "Massless": false,
        "Material": 1312,
        "PivotOffset": {
          "position": [
            0,
            -0.0401921831,
            0.023849627
          ],
          "rotation": [
            1,
            -1.99520325e-23,
            -2.44929371e-16,
            -2.44929371e-16,
            -1.62920685e-7,
            -1,
            -1.99520294e-23,
            1,
            -1.62920685e-7
          ]
        },
        "Reflectance": 0,
        "Transparency": 0.00499999989,
        "size": [
          1.93214488,
          1.34685099,
          1.11439264
        ],
        "Name": "Cloth",
        "LocalCFrame": {
          "position": [
            -0.152008,
            0.81829,
            -0.328919
          ],
          "rotation": [
            1,
            0,
            0,
            0,
            0.999999,
            0,
            0,
            0,
            0.999997
          ]
        }
      }
    },
    {
      "id": "RBX458BCB4E391E44DD801A7C6570E023AB",
      "parent": "RBX0FDA41449F634F4CACD24450356743B5",
      "class": "Motor6D",
      "name": "SportsBallInner3Motor6D",
      "properties": {
        "C0": {
          "position": [
            -0.152005598,
            0.818291485,
            -0.328915447
          ],
          "rotation": [
            1,
            0,
            0,
            0,
            1,
            0,
            0,
            0,
            1
          ]
        },
        "C1": {
          "position": [
            0,
            0,
            0
          ],
          "rotation": [
            1,
            0,
            0,
            0,
            1,
            0,
            0,
            0,
            1
          ]
        },
        "Enabled": true,
        "Part0": "RBXA47C3A5EC5AC43309F1B64B9979E394B",
        "Part1": "RBX0FDA41449F634F4CACD24450356743B5",
        "Name": "SportsBallInner3Motor6D"
      }
    },
    {
      "id": "RBX39D5AA6B20F74A61B3C9F7D40895EA5A",
      "parent": "RBX4DD1C48A8ADA4CCAA41B14F3EB849828",
      "class": "MeshPart",
      "name": "color5",
      "properties": {
        "HasSkinnedMesh": true,
        "MeshId": "rbxassetid://89304112355698",
        "RenderFidelity": 0,
        "TextureID": null,
        "Anchored": false,
        "CanCollide": true,
        "CanQuery": true,
        "CanTouch": true,
        "Color3uint8": [
          0.639216,
          0.635294,
          0.647059
        ],
        "Massless": false,
        "Material": 272,
        "PivotOffset": {
          "position": [
            -3.98897271e-7,
            -0.0326943323,
            0.00456566783
          ],
          "rotation": [
            1,
            -1.99520325e-23,
            -2.44929371e-16,
            -2.44929371e-16,
            -1.62920685e-7,
            -1,
            -1.99520294e-23,
            1,
            -1.62920685e-7
          ]
        },
        "Reflectance": 0,
        "Transparency": 0,
        "size": [
          1.915133,
          1.32845008,
          1.10449505
        ],
        "Name": "color5",
        "LocalCFrame": {
          "position": [
            -0.151153,
            0.818309,
            -0.3302
          ],
          "rotation": [
            1,
            0,
            0,
            0,
            0.999999,
            0,
            0,
            0,
            0.999997
          ]
        }
      }
    },
    {
      "id": "RBX9A6F85B60BDB4F0297EEC5C00A1D5099",
      "parent": "RBX39D5AA6B20F74A61B3C9F7D40895EA5A",
      "class": "Motor6D",
      "name": "SportsBallInnerMotor6D",
      "properties": {
        "C0": {
          "position": [
            -0.151168302,
            0.818309546,
            -0.330230474
          ],
          "rotation": [
            1,
            0,
            0,
            0,
            1,
            0,
            0,
            0,
            1
          ]
        },
        "C1": {
          "position": [
            0,
            0,
            0
          ],
          "rotation": [
            1,
            0,
            0,
            0,
            1,
            0,
            0,
            0,
            1
          ]
        },
        "Enabled": true,
        "Part0": "RBXA47C3A5EC5AC43309F1B64B9979E394B",
        "Part1": "RBX39D5AA6B20F74A61B3C9F7D40895EA5A",
        "Name": "SportsBallInnerMotor6D"
      }
    },
    {
      "id": "RBXA47C3A5EC5AC43309F1B64B9979E394B",
      "parent": "RBX4DD1C48A8ADA4CCAA41B14F3EB849828",
      "class": "Part",
      "name": "RootPart",
      "properties": {
        "shape": 1,
        "Anchored": false,
        "CanCollide": true,
        "CanQuery": true,
        "CanTouch": true,
        "Color3uint8": [
          0.639216,
          0.635294,
          0.647059
        ],
        "Massless": false,
        "Material": 256,
        "PivotOffset": {
          "position": [
            0,
            0,
            0
          ],
          "rotation": [
            1,
            0,
            0,
            0,
            1,
            0,
            0,
            0,
            1
          ]
        },
        "Reflectance": 0,
        "Transparency": 1,
        "size": [
          1.48719704,
          1.48719704,
          0.743598521
        ],
        "Name": "RootPart",
        "LocalCFrame": {
          "position": [
            0,
            0,
            0
          ],
          "rotation": [
            1,
            0,
            0,
            0,
            0.999999,
            0,
            0,
            0,
            0.999997
          ]
        }
      }
    },
    {
      "id": "RBXD4B73C036A3746789510BA78BE43E3A9",
      "parent": "RBXA47C3A5EC5AC43309F1B64B9979E394B",
      "class": "Bone",
      "name": "Bone.002",
      "properties": {
        "CFrame": {
          "position": [
            -0.260988116,
            1.44881594,
            -0.665731549
          ],
          "rotation": [
            1,
            1.96121206e-7,
            -5.91453908e-9,
            1.96121206e-7,
            -1,
            2.54588542e-7,
            -5.91448934e-9,
            -2.54588542e-7,
            -1
          ]
        },
        "Visible": false,
        "Name": "Bone.002"
      }
    },
    {
      "id": "RBX70B9897AB9E74A93AA389323E0986BAA",
      "parent": "RBXD4B73C036A3746789510BA78BE43E3A9",
      "class": "Bone",
      "name": "Bone.003",
      "properties": {
        "CFrame": {
          "position": [
            0,
            0.807774603,
            0.00000314712543
          ],
          "rotation": [
            0.833220959,
            -0.551594794,
            -0.0385488309,
            -0.0385483615,
            -0.127493337,
            0.99109,
            -0.551594853,
            -0.824310958,
            -0.127493188
          ]
        },
        "Visible": false,
        "Name": "Bone.003"
      }
    },
    {
      "id": "RBXD8CCDA130A104DC5A08B05230B9815E6",
      "parent": "RBXA47C3A5EC5AC43309F1B64B9979E394B",
      "class": "Bone",
      "name": "Bone",
      "properties": {
        "CFrame": {
          "position": [
            -0.0413482711,
            1.44881594,
            -0.66573143
          ],
          "rotation": [
            1,
            -5.0790149e-8,
            2.68431393e-7,
            -5.07902165e-8,
            -1,
            2.54588571e-7,
            2.68431393e-7,
            -2.54588571e-7,
            -1
          ]
        },
        "Visible": false,
        "Name": "Bone"
      }
    },
    {
      "id": "RBX5ACCEDFB8DBE4ADDB804BDA009126CDF",
      "parent": "RBXD8CCDA130A104DC5A08B05230B9815E6",
      "class": "Bone",
      "name": "Bone.001",
      "properties": {
        "CFrame": {
          "position": [
            0,
            0.807774603,
            0.00000314712543
          ],
          "rotation": [
            0.833975494,
            0.551594913,
            -0.0151050687,
            0.102193207,
            -0.127493128,
            0.986560941,
            0.542256057,
            -0.824311078,
            -0.162695408
          ]
        },
        "Visible": false,
        "Name": "Bone.001"
      }
    }
  ]
}
