{
  "format": "overlay_json_v1",
  "kind": "morph_bundle",
  "version": 1,
  "asset_id": "morph_2767-7",
  "name": "7",
  "source_file": "2767-7.rbxmx",
  "anchor": "HumanoidRootPart",
  "anchor_candidates": [
    "HumanoidRootPart",
    "UpperTorso",
    "Torso",
    "Head"
  ],
  "jiggle": false,
  "root_cframe": {
    "position": [
      -4084.27197,
      31223.8301,
      -4227.60205
    ],
    "rotation": [
      1,
      0,
      0,
      0,
      1,
      0,
      0,
      0,
      1
    ]
  },
  "class_counts": {
    "Folder": 1,
    "Model": 3,
    "Part": 12,
    "SpecialMesh": 10,
    "UnionOperation": 1
  },
  "nodes": [
    {
      "id": "RBX8E4FAE62B0174E8295A498E1CBFF15DA",
      "parent": null,
      "class": "Folder",
      "name": "7",
      "properties": {
        "Name": "7"
      }
    },
    {
      "id": "RBX60B3514BBA5E4E5C91E5578425E1438A",
      "parent": "RBX8E4FAE62B0174E8295A498E1CBFF15DA",
      "class": "Model",
      "name": "Orbs",
      "properties": {
        "PrimaryPart": "RBX5AA9D955E9F043769FF543B47F3828BC",
        "Name": "Orbs"
      }
    },
    {
      "id": "RBX94EF9B6355434520B41EDE7537DC31C5",
      "parent": "RBX60B3514BBA5E4E5C91E5578425E1438A",
      "class": "Part",
      "name": "color5",
      "properties": {
        "shape": 1,
        "Anchored": true,
        "CanCollide": false,
        "CanQuery": true,
        "CanTouch": true,
        "Color3uint8": [
          0.972549,
          0.972549,
          0.972549
        ],
        "Massless": false,
        "Material": 272,
        "PivotOffset": {
          "position": [
            0,
            0,
            0
          ],
          "rotation": [
            1,
            0,
            0,
            0,
            1,
            0,
            0,
            0,
            1
          ]
        },
        "Reflectance": 0,
        "Transparency": 1,
        "size": [
          0.690325558,
          0.774196982,
          0.645164192
        ],
        "Name": "color5",
        "LocalCFrame": {
          "position": [
            0.00708,
            -1.0391,
            -0.49707
          ],
          "rotation": [
            -0.999734,
            0,
            0.023081,
            0,
            1,
            0,
            -0.023081,
            0,
            -0.999734
          ]
        }
      }
    },
    {
      "id": "RBX121FE22A79FF45AE8773B1B76F217D53",
      "parent": "RBX94EF9B6355434520B41EDE7537DC31C5",
      "class": "SpecialMesh",
      "name": "Mesh",
      "properties": {
        "MeshType": 3,
        "MeshId": null,
        "TextureId": null,
        "Offset": [
          0,
          0,
          0
        ],
        "Scale": [
          1,
          1,
          1
        ],
        "VertexColor": [
          1,
          1,
          1
        ],
        "Name": "Mesh"
      }
    },
    {
      "id": "RBXF152338536C9409EA9370F920D7BF993",
      "parent": "RBX60B3514BBA5E4E5C91E5578425E1438A",
      "class": "Part",
      "name": "color5",
      "properties": {
        "shape": 1,
        "Anchored": true,
        "CanCollide": false,
        "CanQuery": true,
        "CanTouch": true,
        "Color3uint8": [
          0.972549,
          0.972549,
          0.972549
        ],
        "Massless": false,
        "Material": 272,
        "PivotOffset": {
          "position": [
            0,
            0,
            0
          ],
          "rotation": [
            1,
            0,
            0,
            0,
            1,
            0,
            0,
            0,
            1
          ]
        },
        "Reflectance": 0,
        "Transparency": 1,
        "size": [
          0.849628627,
          0.952854753,
          0.794045627
        ],
        "Name": "color5",
        "LocalCFrame": {
          "position": [
            0.18921,
            -1.1973,
            -0.57324
          ],
          "rotation": [
            -0.999734,
            0,
            0.023081,
            0,
            1,
            0,
            -0.023081,
            0,
            -0.999734
          ]
        }
      }
    },
    {
      "id": "RBX2455874A4AE34FC5ACFAA2F3C73C0DB5",
      "parent": "RBXF152338536C9409EA9370F920D7BF993",
      "class": "SpecialMesh",
      "name": "Mesh",
      "properties": {
        "MeshType": 3,
        "MeshId": null,
        "TextureId": null,
        "Offset": [
          0,
          0,
          0
        ],
        "Scale": [
          1,
          1,
          1
        ],
        "VertexColor": [
          1,
          1,
          1
        ],
        "Name": "Mesh"
      }
    },
    {
      "id": "RBX30C4261F3DBF424EB7937958F9A4C315",
      "parent": "RBX60B3514BBA5E4E5C91E5578425E1438A",
      "class": "Part",
      "name": "color5",
      "properties": {
        "shape": 1,
        "Anchored": true,
        "CanCollide": false,
        "CanQuery": true,
        "CanTouch": true,
        "Color3uint8": [
          0.972549,
          0.972549,
          0.972549
        ],
        "Massless": false,
        "Material": 272,
        "PivotOffset": {
          "position": [
            0,
            0,
            0
          ],
          "rotation": [
            1,
            0,
            0,
            0,
            1,
            0,
            0,
            0,
            1
          ]
        },
        "Reflectance": 0,
        "Transparency": 1,
        "size": [
          0.849628627,
          0.952854753,
          0.794045627
        ],
        "Name": "color5",
        "LocalCFrame": {
          "position": [
            -0.22876,
            -1.1973,
            -0.58496
          ],
          "rotation": [
            -0.999734,
            0,
            0.023081,
            0,
            1,
            0,
            -0.023081,
            0,
            -0.999734
          ]
        }
      }
    },
    {
      "id": "RBX3B4473C8221447FC914515F6EE94F1E4",
      "parent": "RBX30C4261F3DBF424EB7937958F9A4C315",
      "class": "SpecialMesh",
      "name": "Mesh",
      "properties": {
        "MeshType": 3,
        "MeshId": null,
        "TextureId": null,
        "Offset": [
          0,
          0,
          0
        ],
        "Scale": [
          1,
          1,
          1
        ],
        "VertexColor": [
          1,
          1,
          1
        ],
        "Name": "Mesh"
      }
    },
    {
      "id": "RBX3F3432A58CE548C7B3DED7B9DBA41BF6",
      "parent": "RBX60B3514BBA5E4E5C91E5578425E1438A",
      "class": "Part",
      "name": "Particle1",
      "properties": {
        "shape": 1,
        "Anchored": true,
        "CanCollide": false,
        "CanQuery": true,
        "CanTouch": true,
        "Color3uint8": [
          1,
          0.580392,
          0.580392
        ],
        "Massless": false,
        "Material": 272,
        "PivotOffset": {
          "position": [
            0,
            0,
            0
          ],
          "rotation": [
            1,
            0,
            0,
            0,
            1,
            0,
            0,
            0,
            1
          ]
        },
        "Reflectance": 0,
        "Transparency": 1,
        "size": [
          0.114335626,
          0.114335626,
          0.114335626
        ],
        "Name": "Particle1",
        "LocalCFrame": {
          "position": [
            0.00171,
            -1.336,
            -0.91309
          ],
          "rotation": [
            -0.999994,
            -0.001819,
            -0.003702,
            0.001913,
            -0.999669,
            -0.0258,
            -0.003654,
            -0.025806,
            0.999665
          ]
        }
      }
    },
    {
      "id": "RBX5AA16FC826AB46ECB3F368C3231EB66F",
      "parent": "RBX60B3514BBA5E4E5C91E5578425E1438A",
      "class": "Part",
      "name": "color5",
      "properties": {
        "shape": 1,
        "Anchored": true,
        "CanCollide": false,
        "CanQuery": true,
        "CanTouch": true,
        "Color3uint8": [
          0.972549,
          0.972549,
          0.972549
        ],
        "Massless": false,
        "Material": 272,
        "PivotOffset": {
          "position": [
            0,
            0,
            0
          ],
          "rotation": [
            1,
            0,
            0,
            0,
            1,
            0,
            0,
            0,
            1
          ]
        },
        "Reflectance": 0,
        "Transparency": 1,
        "size": [
          0.40817818,
          0.359013885,
          0.603692114
        ],
        "Name": "color5",
        "LocalCFrame": {
          "position": [
            -0.00196,
            -0.9707,
            -0.95996
          ],
          "rotation": [
            -0.999992,
            0.003824,
            -0.001546,
            0.001914,
            0.098022,
            -0.995182,
            -0.003654,
            -0.995178,
            -0.098029
          ]
        }
      }
    },
    {
      "id": "RBXE6245AB7CD834F4EB41345DD1A5216F2",
      "parent": "RBX5AA16FC826AB46ECB3F368C3231EB66F",
      "class": "SpecialMesh",
      "name": "Mesh",
      "properties": {
        "MeshType": 3,
        "MeshId": null,
        "TextureId": null,
        "Offset": [
          0,
          0,
          0
        ],
        "Scale": [
          1,
          1,
          1
        ],
        "VertexColor": [
          1,
          1,
          1
        ],
        "Name": "Mesh"
      }
    },
    {
      "id": "RBX899F07A46F3649319B6396DC42DA9203",
      "parent": "RBX60B3514BBA5E4E5C91E5578425E1438A",
      "class": "Part",
      "name": "color5",
      "properties": {
        "shape": 1,
        "Anchored": true,
        "CanCollide": false,
        "CanQuery": true,
        "CanTouch": true,
        "Color3uint8": [
          0.972549,
          0.972549,
          0.972549
        ],
        "Massless": false,
        "Material": 272,
        "PivotOffset": {
          "position": [
            0,
            0,
            0
          ],
          "rotation": [
            1,
            0,
            0,
            0,
            1,
            0,
            0,
            0,
            1
          ]
        },
        "Reflectance": 0,
        "Transparency": 1,
        "size": [
          0.40817818,
          0.359013885,
          0.603692114
        ],
        "Name": "color5",
        "LocalCFrame": {
          "position": [
            -0.00196,
            -0.7832,
            -0.87451
          ],
          "rotation": [
            -0.999993,
            0.003937,
            0.001231,
            0.001914,
            0.707117,
            -0.707094,
            -0.003654,
            -0.707087,
            -0.707119
          ]
        }
      }
    },
    {
      "id": "RBX8BFBBD488A7444D6BF2381472F8E72B4",
      "parent": "RBX899F07A46F3649319B6396DC42DA9203",
      "class": "SpecialMesh",
      "name": "Mesh",
      "properties": {
        "MeshType": 3,
        "MeshId": null,
        "TextureId": null,
        "Offset": [
          0,
          0,
          0
        ],
        "Scale": [
          1,
          1,
          1
        ],
        "VertexColor": [
          1,
          1,
          1
        ],
        "Name": "Mesh"
      }
    },
    {
      "id": "RBX24559A9AFE044237B11F136510249565",
      "parent": "RBX60B3514BBA5E4E5C91E5578425E1438A",
      "class": "Part",
      "name": "color1",
      "properties": {
        "shape": 1,
        "Anchored": true,
        "CanCollide": false,
        "CanQuery": true,
        "CanTouch": true,
        "Color3uint8": [
          1,
          0.580392,
          0.580392
        ],
        "Massless": false,
        "Material": 272,
        "PivotOffset": {
          "position": [
            0,
            0,
            0
          ],
          "rotation": [
            1,
            0,
            0,
            0,
            1,
            0,
            0,
            0,
            1
          ]
        },
        "Reflectance": 0,
        "Transparency": 1,
        "size": [
          0.444838345,
          0.394036114,
          0.210263729
        ],
        "Name": "color1",
        "LocalCFrame": {
          "position": [
            -0.00196,
            -1.1504,
            -0.97949
          ],
          "rotation": [
            -0.999992,
            0.003862,
            -0.001447,
            0.001914,
            0.12366,
            -0.992323,
            -0.003654,
            -0.992319,
            -0.123666
          ]
        }
      }
    },
    {
      "id": "RBX9F01DF2D10A84258919AEA2059D8A38D",
      "parent": "RBX24559A9AFE044237B11F136510249565",
      "class": "SpecialMesh",
      "name": "Mesh",
      "properties": {
        "MeshType": 3,
        "MeshId": null,
        "TextureId": null,
        "Offset": [
          0,
          0,
          0
        ],
        "Scale": [
          1,
          1,
          1
        ],
        "VertexColor": [
          1,
          1,
          1
        ],
        "Name": "Mesh"
      }
    },
    {
      "id": "RBXE6F92AD31E65461AACF01DCD433E5B6E",
      "parent": "RBX60B3514BBA5E4E5C91E5578425E1438A",
      "class": "Part",
      "name": "color1",
      "properties": {
        "shape": 1,
        "Anchored": true,
        "CanCollide": false,
        "CanQuery": true,
        "CanTouch": true,
        "Color3uint8": [
          1,
          0.580392,
          0.580392
        ],
        "Massless": false,
        "Material": 272,
        "PivotOffset": {
          "position": [
            0,
            0,
            0
          ],
          "rotation": [
            1,
            0,
            0,
            0,
            1,
            0,
            0,
            0,
            1
          ]
        },
        "Reflectance": 0,
        "Transparency": 1,
        "size": [
          0.348596901,
          0.316288263,
          0.328011125
        ],
        "Name": "color1",
        "LocalCFrame": {
          "position": [
            0.00195,
            -1.2324,
            -0.92285
          ],
          "rotation": [
            -0.999992,
            0.003862,
            -0.001447,
            0.001914,
            0.12366,
            -0.992323,
            -0.003654,
            -0.992319,
            -0.123666
          ]
        }
      }
    },
    {
      "id": "RBXCA9F1E53E8F8402EB1140430235E056D",
      "parent": "RBXE6F92AD31E65461AACF01DCD433E5B6E",
      "class": "SpecialMesh",
      "name": "Mesh",
      "properties": {
        "MeshType": 3,
        "MeshId": null,
        "TextureId": null,
        "Offset": [
          0,
          0,
          0
        ],
        "Scale": [
          1,
          1,
          1
        ],
        "VertexColor": [
          1,
          1,
          1
        ],
        "Name": "Mesh"
      }
    },
    {
      "id": "RBX77123E226D05405DADFF72898CEAD47A",
      "parent": "RBX60B3514BBA5E4E5C91E5578425E1438A",
      "class": "Part",
      "name": "color5",
      "properties": {
        "shape": 1,
        "Anchored": true,
        "CanCollide": false,
        "CanQuery": true,
        "CanTouch": true,
        "Color3uint8": [
          0.972549,
          0.972549,
          0.972549
        ],
        "Massless": false,
        "Material": 272,
        "PivotOffset": {
          "position": [
            0,
            0,
            0
          ],
          "rotation": [
            1,
            0,
            0,
            0,
            1,
            0,
            0,
            0,
            1
          ]
        },
        "Reflectance": 0,
        "Transparency": 1,
        "size": [
          0.40817818,
          0.359013885,
          0.603692114
        ],
        "Name": "color5",
        "LocalCFrame": {
          "position": [
            -0.00244,
            -0.711,
            -0.72754
          ],
          "rotation": [
            -0.999992,
            0.002262,
            0.003449,
            0.001913,
            0.995185,
            -0.097999,
            -0.003654,
            -0.097991,
            -0.995182
          ]
        }
      }
    },
    {
      "id": "RBX9B3AA979C368403BACEEB30207522BF4",
      "parent": "RBX77123E226D05405DADFF72898CEAD47A",
      "class": "SpecialMesh",
      "name": "Mesh",
      "properties": {
        "MeshType": 3,
        "MeshId": null,
        "TextureId": null,
        "Offset": [
          0,
          0,
          0
        ],
        "Scale": [
          1,
          1,
          1
        ],
        "VertexColor": [
          1,
          1,
          1
        ],
        "Name": "Mesh"
      }
    },
    {
      "id": "RBX5AA9D955E9F043769FF543B47F3828BC",
      "parent": "RBX60B3514BBA5E4E5C91E5578425E1438A",
      "class": "Part",
      "name": "Middle",
      "properties": {
        "shape": 1,
        "Anchored": true,
        "CanCollide": false,
        "CanQuery": true,
        "CanTouch": true,
        "Color3uint8": [
          0.972549,
          0.972549,
          0.972549
        ],
        "Massless": false,
        "Material": 272,
        "PivotOffset": {
          "position": [
            0,
            0,
            0
          ],
          "rotation": [
            1,
            0,
            0,
            0,
            1,
            0,
            0,
            0,
            1
          ]
        },
        "Reflectance": 0,
        "Transparency": 1,
        "size": [
          2,
          2,
          1
        ],
        "Name": "Middle",
        "LocalCFrame": {
          "position": [
            0,
            0,
            0
          ],
          "rotation": [
            1,
            0,
            0,
            0,
            1,
            0,
            0,
            0,
            1
          ]
        }
      }
    },
    {
      "id": "RBX04218722AAC349E0A743A7B64FBD7248",
      "parent": "RBX5AA9D955E9F043769FF543B47F3828BC",
      "class": "SpecialMesh",
      "name": "Mesh",
      "properties": {
        "MeshType": 5,
        "MeshId": "rbxassetid://12221758",
        "TextureId": null,
        "Offset": [
          0,
          0,
          0
        ],
        "Scale": [
          1,
          1,
          1
        ],
        "VertexColor": [
          1,
          1,
          1
        ],
        "Name": "Mesh"
      }
    },
    {
      "id": "RBXC569503A18664EB6BC68D15A3E7F157F",
      "parent": "RBX60B3514BBA5E4E5C91E5578425E1438A",
      "class": "UnionOperation",
      "name": "Lock",
      "properties": {
        "UsePartColor": true,
        "Anchored": true,
        "CanCollide": false,
        "CanQuery": true,
        "CanTouch": true,
        "Color3uint8": [
          0.356863,
          0.364706,
          0.411765
        ],
        "Massless": false,
        "Material": 272,
        "PivotOffset": {
          "position": [
            0,
            0,
            0
          ],
          "rotation": [
            1,
            0,
            0,
            0,
            1,
            0,
            0,
            0,
            1
          ]
        },
        "Reflectance": 0,
        "Transparency": 1,
        "size": [
          0.91688019,
          0.817390859,
          0.535847962
        ],
        "Name": "Lock",
        "LocalCFrame": {
          "position": [
            -0.00977,
            -0.959,
            -0.88184
          ],
          "rotation": [
            0,
            0,
            -1,
            0.984808,
            -0.173648,
            0,
            -0.173648,
            -0.984808,
            0
          ]
        }
      }
    },
    {
      "id": "RBX68CA37E2385C42CE8CAEC56F8E829FEA",
      "parent": "RBX8E4FAE62B0174E8295A498E1CBFF15DA",
      "class": "Model",
      "name": "LowerStaticA",
      "properties": {
        "PrimaryPart": "RBXD5BB1E46494046818AECAC7F8927050D",
        "Name": "LowerStaticA"
      }
    },
    {
      "id": "RBXD5BB1E46494046818AECAC7F8927050D",
      "parent": "RBX68CA37E2385C42CE8CAEC56F8E829FEA",
      "class": "Part",
      "name": "Middle",
      "properties": {
        "shape": 1,
        "Anchored": true,
        "CanCollide": false,
        "CanQuery": true,
        "CanTouch": true,
        "Color3uint8": [
          0.972549,
          0.972549,
          0.972549
        ],
        "Massless": false,
        "Material": 272,
        "PivotOffset": {
          "position": [
            0,
            0,
            0
          ],
          "rotation": [
            1,
            0,
            0,
            0,
            1,
            0,
            0,
            0,
            1
          ]
        },
        "Reflectance": 0,
        "Transparency": 1,
        "size": [
          2,
          2,
          1
        ],
        "Name": "Middle",
        "LocalCFrame": {
          "position": [
            -23,
            33.6816,
            -6.00098
          ],
          "rotation": [
            1,
            0,
            0,
            0,
            1,
            0,
            0,
            0,
            1
          ]
        }
      }
    },
    {
      "id": "RBX7AEA32261AB14EB99B148E1600439AA1",
      "parent": "RBXD5BB1E46494046818AECAC7F8927050D",
      "class": "SpecialMesh",
      "name": "Mesh",
      "properties": {
        "MeshType": 5,
        "MeshId": "rbxassetid://12221758",
        "TextureId": null,
        "Offset": [
          0,
          0,
          0
        ],
        "Scale": [
          1,
          1,
          1
        ],
        "VertexColor": [
          1,
          1,
          1
        ],
        "Name": "Mesh"
      }
    },
    {
      "id": "RBXE453CD24B59E437D9BCFBC7443E15652",
      "parent": "RBX8E4FAE62B0174E8295A498E1CBFF15DA",
      "class": "Model",
      "name": "Rod",
      "properties": {
        "PrimaryPart": null,
        "Name": "Rod"
      }
    },
    {
      "id": "RBXBD2B110D64B34038A47BFA0E6A45E87F",
      "parent": "RBXE453CD24B59E437D9BCFBC7443E15652",
      "class": "Part",
      "name": "Middle",
      "properties": {
        "shape": 1,
        "Anchored": true,
        "CanCollide": false,
        "CanQuery": true,
        "CanTouch": true,
        "Color3uint8": [
          1,
          0,
          0
        ],
        "Massless": false,
        "Material": 256,
        "PivotOffset": {
          "position": [
            0,
            0,
            0
          ],
          "rotation": [
            1,
            0,
            0,
            0,
            1,
            0,
            0,
            0,
            1
          ]
        },
        "Reflectance": 0,
        "Transparency": 1,
        "size": [
          0.177276984,
          0.177276984,
          0.177276984
        ],
        "Name": "Middle",
        "LocalCFrame": {
          "position": [
            -23,
            32.6992,
            -6.54785
          ],
          "rotation": [
            1,
            0,
            0,
            0,
            1,
            0,
            0,
            0,
            1
          ]
        }
      }
    }
  ]
}
